{
  "bg":          "#0f1511",
  "bg_alt":      "#404942",
  "surface":     "#1b211d",
  "surface2":    "#262b27",
  "overlay":     "#303632",

  "fg":          "#dfe4dd",
  "fg_dim":      "#c0c9c0",

  "accent":      "#91d5ac",
  "accent_alt":  "#b5ccbb",

  "red":         "#ffb4ab",
  "orange":      "#224c59",
  "yellow":      "#374b3e",
  "green":       "#a4cddc",
  "teal":        "#045233",
  "blue":        "#91d5ac",
  "sky":         "#b5ccbb",
  "mauve":       "#a4cddc",
  "pink":        "#93000a",
  "lavender":    "#d0e8d6",

  "border_active":   "#91d5ac",
  "border_inactive": "#404942",

  "shadow":      "#000000"
}
